toontown_utils/__init__.py
toontown_utils/cog/__init__.py
toontown_utils/cog/CogActor.py
toontown_utils/cog/CogBody.py
toontown_utils/cog/CogGlobals.py
toontown_utils/cog/CogLoader.py
toontown_utils/cog/Department.py
toontown_utils/cog/TemplateCog.py
toontown_utils/LoaderUtils.py
toontown_utils/TemplateManager.py
toontown_utils/toon/__init__.py
toontown_utils/toon/ToonActor.py
toontown_utils/toon/ToonHead.py
toontown_utils/toon/ToonLoader.py
toontown_utils/toon/ToonPart.py
toontown_utils/toon/ToonSpecies.py
toontown_utils-2.0.1.dist-info/LICENSE
toontown_utils-2.0.1.dist-info/METADATA
toontown_utils-2.0.1.dist-info/WHEEL
toontown_utils-2.0.1.dist-info/RECORD
