Metadata-Version: 2.1
Name: toontown-utils
Version: 2.0.1
Summary: Toontown-specific utilities for Panda3D
Home-page: https://github.com/demiurgeQuantified/ToontownUtils
License: MIT
Author: albion
Author-email: 8355611+demiurgeQuantified@users.noreply.github.com
Requires-Python: >=3.11,<4.0
Classifier: License :: OSI Approved :: MIT License
Classifier: Programming Language :: Python :: 3
Classifier: Programming Language :: Python :: 3.11
Requires-Dist: Panda3D (>=1.10.13.post1,<2.0.0)
Project-URL: Repository, https://github.com/demiurgeQuantified/ToontownUtils
